MANIFEST.in
setup.py
esymod/__init__.py
esymod/basic.py
esymod/blocks.py
esymod/evaluates.py
esymod/example.py
esymod/file_dataset.py
esymod/gans.py
esymod/h5_dataset.py
esymod/hilberts.py
esymod/kans.py
esymod/main.py
esymod/manipulators.py
esymod/pggan.py
esymod/rnns.py
esymod/sparse_dataset.py
esymod/taylor.py
esymod/train.py
esymod.egg-info/PKG-INFO
esymod.egg-info/SOURCES.txt
esymod.egg-info/dependency_links.txt
esymod.egg-info/top_level.txt