Metadata-Version: 2.1
Name: esymod
Version: 39.2025.7.31.14.38
Summary: a python lib for project files
Home-page: http://www.xxxxx.com/
Author: Quanfa
Author-email: quanfa@tju.edu.cn
License: MIT
